parsemd.py
MdUtil-0.0.1.dist-info/LICENSE.txt
MdUtil-0.0.1.dist-info/METADATA
MdUtil-0.0.1.dist-info/WHEEL
MdUtil-0.0.1.dist-info/top_level.txt
MdUtil-0.0.1.dist-info/RECORD
