Metadata-Version: 2.1
Name: MdUtil
Version: 0.0.1
Summary: Markdown utility for python
Home-page: https://github.com/Theodore-Robinson/MdUtil
License: UNKNOWN
Platform: UNKNOWN
Classifier: Programming Language :: Python :: 3
Classifier: License :: OSI Approved :: MIT License
Classifier: Operating System :: OS Independent
Provides-Extra: dev
Requires-Dist: autopep8 ; extra == 'dev'
Requires-Dist: flake8 ; extra == 'dev'
